lila/__init__.py
lila/core/__init__.py
lila/core/action.py
lila/core/base.py
lila/core/common.py
lila/core/entity.py
lila/core/field.py
lila/core/link.py
lila/serialization/__init__.py
lila/serialization/marshaler.py
lila/serialization/parser.py
lila/serialization/json/__init__.py
lila/serialization/json/action.py
lila/serialization/json/entity.py
lila/serialization/json/field.py
lila/serialization/json/link.py
lila/serialization/json/marshaler.py
lila/serialization/json/parser.py
lila-1.0.0.dist-info/LICENSE
lila-1.0.0.dist-info/METADATA
lila-1.0.0.dist-info/WHEEL
lila-1.0.0.dist-info/top_level.txt
lila-1.0.0.dist-info/RECORD
