Metadata-Version: 2.1
Name: lila
Version: 1.0.0
Summary: Library to work with Siren protocol
Home-page: https://github.com/KillAChicken/lila
Author: KillAChicken
Author-email: KillAChicken@yandex.ru
License: UNKNOWN
Platform: UNKNOWN
Classifier: License :: OSI Approved :: MIT License
Classifier: Operating System :: OS Independent
Classifier: Programming Language :: Python :: 3
